delta_sdk/__init__.py
delta_sdk/delta_auth.py
delta_sdk-0.0.14.dist-info/METADATA
delta_sdk-0.0.14.dist-info/WHEEL
delta_sdk-0.0.14.dist-info/licenses/LICENSE
delta_sdk-0.0.14.dist-info/RECORD
