Metadata-Version: 2.1
Name: delta_sdk
Version: 0.0.14
Summary: A small package to help authenticate and use dulms api
Project-URL: Homepage, https://github.com/HqNw/dulms_sdk
Project-URL: Bug Tracker, https://github.com/HqNw/dulms_sdk/issues
Author-email: "HqNw(ahmed reda)" <redalabeb166@gmail.com>
License-File: LICENSE
Classifier: Development Status :: 3 - Alpha
Classifier: License :: OSI Approved :: GNU General Public License v3 or later (GPLv3+)
Classifier: Operating System :: OS Independent
Classifier: Programming Language :: Python :: 3
Requires-Python: >=3.7
Requires-Dist: beautifulsoup4
Requires-Dist: requests
